fastaai/__init__.py
fastaai/fastaai.py
fastaai/00.Libraries/01.SCG_HMMs/Archaea_SCG.hmm
fastaai/00.Libraries/01.SCG_HMMs/Bacteria_SCG.hmm
fastaai/00.Libraries/01.SCG_HMMs/Complete_SCG_DB.hmm
FastAAI-0.1.20.dist-info/LICENSE
FastAAI-0.1.20.dist-info/METADATA
FastAAI-0.1.20.dist-info/WHEEL
FastAAI-0.1.20.dist-info/entry_points.txt
FastAAI-0.1.20.dist-info/top_level.txt
FastAAI-0.1.20.dist-info/RECORD
