Metadata-Version: 2.1
Name: FastAAI
Version: 0.1.20
Summary: A rapid estimator for amino acid identity between genomes.
Author: Kenji Gerhardt
Author-email: kenji.gerhardt@gmail.com
Requires-Python: >=3
License-File: LICENSE
Requires-Dist: numpy
Requires-Dist: pyrodigal (==1.0.2)
Requires-Dist: pyhmmer
